.gitignore
LICENSE
MANIFEST.in
README.md
jira-bot
setup.py
config/jira-bot.conf.sample
jira_bot/__init__.py
jira_bot/fancy_grid.py
jira_bot/utils.py
jira_bot.egg-info/PKG-INFO
jira_bot.egg-info/SOURCES.txt
jira_bot.egg-info/dependency_links.txt
jira_bot.egg-info/pbr.json
jira_bot.egg-info/requires.txt
jira_bot.egg-info/top_level.txt
jira_bot/command/__init__.py
jira_bot/command/comment.py
jira_bot/command/create.py
jira_bot/command/list_issue_types.py
jira_bot/command/list_priorities.py
jira_bot/command/list_projects.py
jira_bot/command/list_resolutions.py
jira_bot/command/list_statuses.py
jira_bot/command/list_transitions.py
jira_bot/command/update.py