Metadata-Version: 1.1
Name: jira-bot
Version: 2.0.1
Summary: JIRA Bot
Home-page: http://zaufi.github.io/jira-bot.html
Author: Alex Turbov
Author-email: I.zaufi@gmail.com
License: GNU General Public License v3 or later (GPLv3+)
Download-URL: https://github.com/zaufi/jira-bot/archive/version-2.0.1.tar.gz
Keywords: jira CLI scripting
Platform: UNKNOWN
Classifier: Development Status :: 4 - Beta
Classifier: Environment :: Console
Classifier: Intended Audience :: Developers
Classifier: License :: OSI Approved :: GNU General Public License v3 or later (GPLv3+)
Classifier: Natural Language :: English
Classifier: Operating System :: POSIX :: Linux
Classifier: Programming Language :: Python :: 3
Classifier: Topic :: Utilities
